idli_coco/__init__.py
idli_coco/app.py
idli_coco/idli_coco.jpg
idli_coco/main.py
idli_coco-2.1.1.dist-info/METADATA
idli_coco-2.1.1.dist-info/WHEEL
idli_coco-2.1.1.dist-info/entry_points.txt
idli_coco-2.1.1.dist-info/top_level.txt
idli_coco-2.1.1.dist-info/RECORD
