Metadata-Version: 2.1
Name: idli-coco
Version: 2.1.1
Requires-Dist: streamlit
Requires-Dist: Pillow
